klio_audio/__init__.py
klio_audio/decorators.py
klio_audio/transforms/__init__.py
klio_audio/transforms/_base.py
klio_audio/transforms/audio.py
klio_audio/transforms/io.py
klio_audio-0.1.0.dist-info/METADATA
klio_audio-0.1.0.dist-info/WHEEL
klio_audio-0.1.0.dist-info/top_level.txt
klio_audio-0.1.0.dist-info/RECORD
